{
    "Name": "Heavy Modular Frame",
    "Category": "IndustrialParts_C",
    "Ingredients": [
        {
            "Item": "Desc_ModularFrame",
            "Amount": 5
        },
        {
            "Item": "Desc_SteelPlateReinforced",
            "Amount": 12
        },
        {
            "Item": "Desc_BrassPipe",
            "Amount": 15
        },
        {
            "Item": "Desc_SteelScrew",
            "Amount": 72
        }
    ],
    "Products": [
        {
            "Item": "Desc_ModularFrameHeavy",
            "Amount": 2
        }
    ],
    "ProducedIn": [
        "Build_ManufacturerMk1"
    ],
    "ManufacturingDuration": 48,
    "ManufacturingMenuPriority": 2,
    "$comment": "This is a new file, no old version exists"
}