{
    "Name": "Encased Industrial Beam",
    "Category": "IndustrialParts_C",
    "Ingredients": [
        {
            "Item": "Desc_SteelPlate",
            "Amount": 6
        },
        {
            "Item": "Desc_Cement",
            "Amount": 20
        }
    ],
    "Products": [
        {
            "Item": "Desc_SteelPlateReinforced",
            "Amount": 2
        }
    ],
    "ProducedIn": [
        "Build_AssemblerMk1"
    ],
    "ManufacturingDuration": 20,
    "ManufacturingMenuPriority": 5,
    "$comment": "This file has been removed, no new version exists"
}