{
    "Name": "Solid Biomass Heater",
    "Ingredients": [
        {
            "Item": "Desc_IronPlateReinforced",
            "Amount": 4
        },
        {
            "Item": "Desc_TinPlate",
            "Amount": 10
        },
        {
            "Item": "Desc_Wire",
            "Amount": 20
        },
        {
            "Item": "Desc_Cable",
            "Amount": 5
        }
    ],
    "ManufacturingMenuPriority": 4,
    "$comment": "This file has been removed, no new version exists"
}