{
    "Name": "Radiator",
    "category": "IndustrialParts_C",
    "Ingredients": [
        {
            "Item": "Desc_AluminumPlate",
            "Amount": 12
        },
        {
            "Item": "Desc_CoolingWater",
            "Amount": 4000
        }
    ],
    "Products": [
        {
            "Item": "Desc_AluminumPlateReinforced",
            "Amount": 2
        }
    ],
    "ManufacturingDuration": 16,
    "ManufacturingMenuPriority": 3,
    "ProducedIn": [
        "Build_OilRefinery"
    ],
    "$comment": "This is a new file, no old version exists"
}